[
    {
        "property_id": "18995",
        "title": "Well Positioned 21 Hectares Farm Land at Kuje",
        "description": "A decent farm land is available for sale at Kuje. The land is measuring 21 Hectares and has all the relevant documentation.",
        "listing_type": "Rentals",
        "property_type": "Land",
        "status": "Available",
        "number_of_page_views": 7153,
        "price": "NGN 15,000,000",
        "property_size": "21,000.00 sq. ft",
        "miscellaneous_details": "None",
        "address": "Kuje",
        "city": "Abuja",
        "area": "Not Specified",
        "state": "Not Specified",
        "country": "Nigeria",
        "zip": "Not Specified",
        "location_tags": [
            "Abuja"
        ],
        "contact_info": {
            "contact_address": "Plot 128 Osun Crescent Maitama, Abuja.",
            "phone": "0806 393 3400, 0803 324 9800, 0705 111 6400,",
            "email": "info@abujaproperties.com, abuja@abujaproperties.com"
        },
        "images_urls": [
            "https://www.abujaproperties.com/wp-content/uploads/2016/02/Screen-Shot-2016-01-28-at-6.41.45-PM.png"
        ],
        "advert_page_link": "https://www.abujaproperties.com/properties/21-hectares-farm-land-at-kuje/",
        "page": 21,
        "time_last_updated": 1708057232985
    },
    {
        "property_id": "23189",
        "title": "Brand New Luxury 5 Bedroom Duplex in Wuse 2",
        "description": "An extremely exquisite 5 bedroom luxury apartment (About the best currently in Wuse 2) is available for rent with spacious compound, bright reception with a large roof offering superb living space.",
        "listing_type": "Rentals",
        "property_type": "Housing",
        "status": "Available",
        "number_of_page_views": 1291,
        "price": "NGN 15,000,000",
        "property_size": "Not Specified",
        "miscellaneous_details": {
            "rooms": "5",
            "bedrooms": "7",
            "bathrooms": "7"
        },
        "address": "Not Specified",
        "city": "Abuja, Abuja FCT, FCT,ABUJA",
        "area": "Wuse II",
        "state": "Abuja, Abuja FCT",
        "country": "Nigeria",
        "zip": "Not Specified",
        "location_tags": [
            "Wuse-Ll",
            "Abuja",
            "Abuja-Fct",
            "Fctabuja"
        ],
        "contact_info": {
            "contact_address": "Plot 128 Osun Crescent Maitama, Abuja.",
            "phone": "0806 393 3400, 0803 324 9800, 0705 111 6400,",
            "email": "info@abujaproperties.com, abuja@abujaproperties.com"
        },
        "images_urls": [
            "https://www.abujaproperties.com/wp-content/uploads/2020/06/A1A-676x467.png",
            "https://www.abujaproperties.com/wp-content/uploads/2020/06/A1-1-698x467.png",
            "https://www.abujaproperties.com/wp-content/uploads/2020/06/A2-1-671x467.png",
            "https://www.abujaproperties.com/wp-content/uploads/2020/06/A4-706x467.png",
            "https://www.abujaproperties.com/wp-content/uploads/2020/06/A5-389x467.png"
        ],
        "advert_page_link": "https://www.abujaproperties.com/properties/luxury-5-bedroom-duplex-in-wuse-2/",
        "page": 21,
        "time_last_updated": 1708057234586
    },
    {
        "property_id": "20487",
        "title": "4 units of 3 Bedroom Apartment in Jabi",
        "description": "4 units of 3 bedroom apartment flat with ample parking space, spacious living rooms, spacious bedrooms (all en suite). Massive compounds, in-built wardrobes, 24hrs security, water treatment and borehole, green area.",
        "listing_type": "Rentals",
        "property_type": "Housing",
        "status": "Available",
        "number_of_page_views": 1216,
        "price": "NGN 15,000,000",
        "property_size": "Not Specified",
        "miscellaneous_details": {
            "bedrooms": "3",
            "bathrooms": "3",
            "year_built": "2014",
            "garages": "12",
            "garage_size": "890"
        },
        "address": "Jabi",
        "city": "Abuja FCT",
        "area": "Jabi",
        "state": "Not Specified",
        "country": "Nigeria",
        "zip": "Not Specified",
        "location_tags": [
            "Jabi",
            "Abuja-Fct"
        ],
        "contact_info": {
            "contact_address": "Plot 128 Osun Crescent Maitama, Abuja.",
            "phone": "0806 393 3400, 0803 324 9800, 0705 111 6400,",
            "email": "info@abujaproperties.com, abuja@abujaproperties.com"
        },
        "images_urls": [
            "https://www.abujaproperties.com/wp-content/uploads/2017/01/a1as-653x467.png",
            "https://www.abujaproperties.com/wp-content/uploads/2017/01/aa4-653x467.png",
            "https://www.abujaproperties.com/wp-content/uploads/2017/01/aaaa1-373x467.png",
            "https://www.abujaproperties.com/wp-content/uploads/2017/01/aacs2-662x467.png",
            "https://www.abujaproperties.com/wp-content/uploads/2017/01/aads3-1-657x467.png",
            "https://www.abujaproperties.com/wp-content/uploads/2017/01/advd5-659x467.png",
            "https://www.abujaproperties.com/wp-content/uploads/2017/01/afsgrt123-652x467.png",
            "https://www.abujaproperties.com/wp-content/uploads/2017/01/ave5-655x467.png",
            "https://www.abujaproperties.com/wp-content/uploads/2017/01/axzce4-658x467.png"
        ],
        "advert_page_link": "https://www.abujaproperties.com/properties/4-units-of-3-bedroomapartment-in-jabi/",
        "page": 21,
        "time_last_updated": 1708057236134
    },
    {
        "property_id": "20008",
        "title": "Lovely 4 Bedroom detached House",
        "description": "Exquisitely Finished 4 Bedroom fully detached duplex with a 2 room B/Q, \u00a0for rent \u00a0at Maitama district, Abuja. Features include :- \u00a0King size rooms, All rooms ensuite with wardrobes, with Jacuzzi in the masters bedroom, fully fitted kitchen, Swimming pool, Green area, P.O.P finished with Italian tiled floor, Security house and electric fencing, water treatment plant, ample parking lot with paved compound.",
        "listing_type": "Rentals",
        "property_type": "Housing",
        "status": "Available",
        "number_of_page_views": 1310,
        "price": "NGN 15,000,000",
        "property_size": "3,023.00 sq. ft",
        "miscellaneous_details": {
            "rooms": "4",
            "bedrooms": "5",
            "bathrooms": "4",
            "year_built": "2016",
            "garages": "12",
            "available_from": "2016"
        },
        "address": "Maitama",
        "city": "Maitama",
        "area": "Maitama",
        "state": "Not Specified",
        "country": "Nigeria",
        "zip": "Not Specified",
        "location_tags": [
            "Maitama",
            "Maitama"
        ],
        "contact_info": {
            "contact_address": "Plot 128 Osun Crescent Maitama, Abuja.",
            "phone": "0806 393 3400, 0803 324 9800, 0705 111 6400,",
            "email": "info@abujaproperties.com, abuja@abujaproperties.com"
        },
        "images_urls": [
            "https://www.abujaproperties.com/wp-content/uploads/2016/09/IMAG4122-835x467.jpg",
            "https://www.abujaproperties.com/wp-content/uploads/2016/09/IMAG4095-835x467.jpg",
            "https://www.abujaproperties.com/wp-content/uploads/2016/09/IMAG4097-835x467.jpg",
            "https://www.abujaproperties.com/wp-content/uploads/2016/09/IMAG4100-835x467.jpg",
            "https://www.abujaproperties.com/wp-content/uploads/2016/09/IMAG4102-835x467.jpg",
            "https://www.abujaproperties.com/wp-content/uploads/2016/09/IMAG4108-835x467.jpg",
            "https://www.abujaproperties.com/wp-content/uploads/2016/09/IMAG4109-835x467.jpg",
            "https://www.abujaproperties.com/wp-content/uploads/2016/09/IMAG4111-835x467.jpg",
            "https://www.abujaproperties.com/wp-content/uploads/2016/09/IMAG4114-835x467.jpg",
            "https://www.abujaproperties.com/wp-content/uploads/2016/09/IMAG4115-835x467.jpg",
            "https://www.abujaproperties.com/wp-content/uploads/2016/09/IMAG4117-835x467.jpg",
            "https://www.abujaproperties.com/wp-content/uploads/2016/09/IMAG4121-835x467.jpg",
            "https://www.abujaproperties.com/wp-content/uploads/2016/09/IMAG4120-835x467.jpg"
        ],
        "advert_page_link": "https://www.abujaproperties.com/properties/lovely-4-bedroom-detached-house/",
        "page": 21,
        "time_last_updated": 1708057237690
    },
    {
        "property_id": "25759",
        "title": "Lovely 5 Bedroom Bungalow at Wuse",
        "description": "Spacious and well finished 5 bedroom bungalow with two room boys quarter at Wuse district Abuja is now available for rent.",
        "listing_type": "Rentals",
        "property_type": "Housing",
        "status": "Available",
        "number_of_page_views": 300,
        "price": "NGN 15,000,000",
        "property_size": "1,123.00 sq. ft",
        "miscellaneous_details": {
            "rooms": "5",
            "bedrooms": "6",
            "bathrooms": "6"
        },
        "address": "Not Specified",
        "city": "Abuja, Abuja FCT, FCT,ABUJA",
        "area": "Wuse",
        "state": "Abuja, Abuja FCT, Federal Capital Territory",
        "country": "Nigeria",
        "zip": "Not Specified",
        "location_tags": [
            "Wuse",
            "Abuja",
            "Abuja-Fct",
            "Fctabuja"
        ],
        "contact_info": {
            "contact_address": "Plot 128 Osun Crescent Maitama, Abuja.",
            "phone": "0806 393 3400, 0803 324 9800, 0705 111 6400,",
            "email": "info@abujaproperties.com, abuja@abujaproperties.com"
        },
        "images_urls": [
            "https://www.abujaproperties.com/wp-content/uploads/2023/06/AC1-681x467.png",
            "https://www.abujaproperties.com/wp-content/uploads/2023/06/AC2-683x467.png",
            "https://www.abujaproperties.com/wp-content/uploads/2023/06/AC3-682x467.png",
            "https://www.abujaproperties.com/wp-content/uploads/2023/06/AC4-681x467.png",
            "https://www.abujaproperties.com/wp-content/uploads/2023/06/AC5-683x467.png",
            "https://www.abujaproperties.com/wp-content/uploads/2023/06/AC6-682x467.png",
            "https://www.abujaproperties.com/wp-content/uploads/2023/06/AC7-680x467.png",
            "https://www.abujaproperties.com/wp-content/uploads/2023/06/AC8-683x467.png"
        ],
        "advert_page_link": "https://www.abujaproperties.com/properties/lovely-5-bedroom-bungalow-at-wuse/",
        "page": 21,
        "time_last_updated": 1708057239254
    },
    {
        "property_id": "22697",
        "title": "Decent 5 Bedroom Duplex in Asokoro",
        "description": "A lovely 5 bedroom detached duplex is available for rent in Asokoro district. The property is located at a very serene location with great facilities such as: 2 guest chalets, all rooms en-suite, Swimming pool, study room, ample parking space,wardrobes, 2 Boys Quarters.",
        "listing_type": "Rentals",
        "property_type": "Housing",
        "status": "Available",
        "number_of_page_views": 2009,
        "price": "NGN 15,000,000",
        "property_size": "Not Specified",
        "miscellaneous_details": {
            "rooms": "5",
            "bedrooms": "5",
            "bathrooms": "9",
            "year_built": "2019",
            "garages": "12"
        },
        "address": "Asokoro",
        "city": "Abuja, Abuja FCT, FCT,ABUJA",
        "area": "Asokoro",
        "state": "Abuja, Abuja FCT",
        "country": "Nigeria",
        "zip": "Not Specified",
        "location_tags": [
            "Asokoro",
            "Abuja",
            "Abuja-Fct",
            "Fctabuja"
        ],
        "contact_info": {
            "contact_address": "Plot 128 Osun Crescent Maitama, Abuja.",
            "phone": "0806 393 3400, 0803 324 9800, 0705 111 6400,",
            "email": "info@abujaproperties.com, abuja@abujaproperties.com"
        },
        "images_urls": [
            "https://www.abujaproperties.com/wp-content/uploads/2019/05/AS1.png",
            "https://www.abujaproperties.com/wp-content/uploads/2019/05/AS2-628x467.png",
            "https://www.abujaproperties.com/wp-content/uploads/2019/05/AS3A-621x467.png",
            "https://www.abujaproperties.com/wp-content/uploads/2019/05/AS3-631x467.png",
            "https://www.abujaproperties.com/wp-content/uploads/2019/05/AS4.png",
            "https://www.abujaproperties.com/wp-content/uploads/2019/05/AS5-624x467.png",
            "https://www.abujaproperties.com/wp-content/uploads/2019/05/AS6-632x467.png"
        ],
        "advert_page_link": "https://www.abujaproperties.com/properties/decent-5-bedroom-duplex-in-asokoro/",
        "page": 21,
        "time_last_updated": 1708057240774
    },
    {
        "property_id": "20834",
        "title": "Brand New 3 Bedroom Duplex in Maitama",
        "description": "A well finished and luxury 3 bedroom terrace duplex with Bq is available for rent in Maitama district, Abuja. Facilities include: Spacious sitting room with a big dinning area, all room en suite with visitors toilet,\u00a0well fitted wardrobes and fitted kitchen, \u00a0very good tiles,\u00a0generator, boys quarter,\u00a0ample parking space, Swimming pool, Gatehouse, Fire alarm systems, Cctv cameras,\u00a0good road network,\u00a0Interlocked compound and in a very decent location.",
        "listing_type": "Rentals",
        "property_type": "Housing",
        "status": "Available",
        "number_of_page_views": 1200,
        "price": "NGN 15,000,000",
        "property_size": "Not Specified",
        "miscellaneous_details": {
            "rooms": "3",
            "bedrooms": "3",
            "bathrooms": "3",
            "year_built": "2016",
            "garages": "6"
        },
        "address": "Maitama",
        "city": "Abuja, Abuja FCT, Maitama",
        "area": "Maitama",
        "state": "Not Specified",
        "country": "Nigeria",
        "zip": "Not Specified",
        "location_tags": [
            "Maitama",
            "Abuja",
            "Abuja-Fct",
            "Maitama"
        ],
        "contact_info": {
            "contact_address": "Plot 128 Osun Crescent Maitama, Abuja.",
            "phone": "0806 393 3400, 0803 324 9800, 0705 111 6400,",
            "email": "info@abujaproperties.com, abuja@abujaproperties.com"
        },
        "images_urls": [
            "https://www.abujaproperties.com/wp-content/uploads/2017/05/AMM1-623x467.png",
            "https://www.abujaproperties.com/wp-content/uploads/2017/05/AMM2.png",
            "https://www.abujaproperties.com/wp-content/uploads/2017/05/AMM3-628x467.png",
            "https://www.abujaproperties.com/wp-content/uploads/2017/05/AMM4-631x467.png",
            "https://www.abujaproperties.com/wp-content/uploads/2017/05/AMM5-630x467.png",
            "https://www.abujaproperties.com/wp-content/uploads/2017/05/AMM6.png",
            "https://www.abujaproperties.com/wp-content/uploads/2017/05/AMM7-635x467.png",
            "https://www.abujaproperties.com/wp-content/uploads/2017/05/AMM8-631x467.png",
            "https://www.abujaproperties.com/wp-content/uploads/2017/05/AMM9-627x467.png",
            "https://www.abujaproperties.com/wp-content/uploads/2017/05/AMM10-632x467.png",
            "https://www.abujaproperties.com/wp-content/uploads/2017/05/AMM11-584x467.png"
        ],
        "advert_page_link": "https://www.abujaproperties.com/properties/brand-new-3-bedroom-terrace-duplex-in-maitama/",
        "page": 21,
        "time_last_updated": 1708057242344
    },
    {
        "property_id": "22705",
        "title": "Brand New Luxury 5 Bedroom in Asokoro",
        "description": "A Brand new and tastefully finished 5 bedroom detached mansion is available for rent in Asokoro district Abuja. The floor is fully serviced with great facilities and designs. The internal doors are very solid bullet proof doors with ample area and plenty green area.",
        "listing_type": "Rentals",
        "property_type": "Housing",
        "status": "Available",
        "number_of_page_views": 2468,
        "price": "NGN 15,000,000",
        "property_size": "1,230.00 sq. ft",
        "miscellaneous_details": {
            "rooms": "5",
            "bedrooms": "7",
            "bathrooms": "8",
            "year_built": "2019",
            "garages": "12"
        },
        "address": "Asokoro",
        "city": "Abuja, Abuja FCT, FCT,ABUJA",
        "area": "Asokoro",
        "state": "Abuja, Abuja FCT",
        "country": "Nigeria",
        "zip": "Not Specified",
        "location_tags": [
            "Asokoro",
            "Abuja",
            "Abuja-Fct",
            "Fctabuja"
        ],
        "contact_info": {
            "contact_address": "Plot 128 Osun Crescent Maitama, Abuja.",
            "phone": "0806 393 3400, 0803 324 9800, 0705 111 6400,",
            "email": "info@abujaproperties.com, abuja@abujaproperties.com"
        },
        "images_urls": [
            "https://www.abujaproperties.com/wp-content/uploads/2019/05/AG1.png",
            "https://www.abujaproperties.com/wp-content/uploads/2019/05/AG2-618x467.png",
            "https://www.abujaproperties.com/wp-content/uploads/2019/05/AG3-624x467.png",
            "https://www.abujaproperties.com/wp-content/uploads/2019/05/AG5-634x467.png",
            "https://www.abujaproperties.com/wp-content/uploads/2019/05/AG5B-628x467.png",
            "https://www.abujaproperties.com/wp-content/uploads/2019/05/AG6-629x467.png",
            "https://www.abujaproperties.com/wp-content/uploads/2019/05/AG7.png",
            "https://www.abujaproperties.com/wp-content/uploads/2019/05/AG7A-632x467.png",
            "https://www.abujaproperties.com/wp-content/uploads/2019/05/AG8.png",
            "https://www.abujaproperties.com/wp-content/uploads/2019/05/AG9-623x467.png",
            "https://www.abujaproperties.com/wp-content/uploads/2019/05/AG10.png"
        ],
        "advert_page_link": "https://www.abujaproperties.com/properties/brand-new-luxury-5-bedroom-in-asokoro/",
        "page": 21,
        "time_last_updated": 1708057243898
    },
    {
        "property_id": "154",
        "title": "Office Space for rent in Wuse",
        "description": "A brand new 8 room duplex perfect for office space is available for rent at Wuse.",
        "listing_type": "Rentals",
        "property_type": "Housing",
        "status": "Available",
        "number_of_page_views": 5969,
        "price": "NGN 15,000,000 per annum",
        "property_size": "1,100.00 sq. ft",
        "miscellaneous_details": {
            "property_lot_size": "850.00 ft2",
            "rooms": "8",
            "bedrooms": "8",
            "bathrooms": "8",
            "year_built": "2015-12-09"
        },
        "address": "Wuse zone 2",
        "city": "Abuja",
        "area": "Wuse zone 2",
        "state": "Not Specified",
        "country": "Nigeria",
        "zip": "Not Specified",
        "location_tags": [
            "Wuse-Zone-2",
            "Abuja"
        ],
        "contact_info": "None",
        "images_urls": [
            "https://www.abujaproperties.com/wp-content/uploads/2014/05/IMAG1413-835x467.jpg",
            "https://www.abujaproperties.com/wp-content/uploads/2014/05/IMAG1394-835x467.jpg",
            "https://www.abujaproperties.com/wp-content/uploads/2014/05/IMAG1401-835x467.jpg",
            "https://www.abujaproperties.com/wp-content/uploads/2014/05/IMAG1402-835x467.jpg",
            "https://www.abujaproperties.com/wp-content/uploads/2014/05/IMAG1405-835x467.jpg",
            "https://www.abujaproperties.com/wp-content/uploads/2014/05/IMAG1407-835x467.jpg",
            "https://www.abujaproperties.com/wp-content/uploads/2014/05/IMAG1409-835x467.jpg",
            "https://www.abujaproperties.com/wp-content/uploads/2014/05/IMAG1410-835x467.jpg",
            "https://www.abujaproperties.com/wp-content/uploads/2014/05/IMAG1411-835x467.jpg"
        ],
        "advert_page_link": "https://www.abujaproperties.com/properties/officespacewuse/",
        "page": 21,
        "time_last_updated": 1708057245554
    },
    {
        "property_id": "19946",
        "title": "2 Bedroom House for Sale at Gaduwa",
        "description": "Very decent and spacious 2 bedroom house is available at Gaduwa Abuja for sale. This house has ample parking space at its within a residential location.",
        "listing_type": "Rentals",
        "property_type": "Housing",
        "status": "Available",
        "number_of_page_views": 2221,
        "price": "NGN 15,000,000",
        "property_size": "Not Specified",
        "miscellaneous_details": {
            "rooms": "2",
            "bedrooms": "2",
            "bathrooms": "2",
            "year_built": "2013"
        },
        "address": "Gaduwa",
        "city": "Abuja FCT",
        "area": "Other Locations",
        "state": "Not Specified",
        "country": "Nigeria",
        "zip": "Not Specified",
        "location_tags": [
            "Other-Locations",
            "Abuja-Fct"
        ],
        "contact_info": {
            "contact_address": "Plot 128 Osun Crescent Maitama, Abuja.",
            "phone": "0806 393 3400, 0803 324 9800, 0705 111 6400,",
            "email": "info@abujaproperties.com, abuja@abujaproperties.com"
        },
        "images_urls": [
            "https://www.abujaproperties.com/wp-content/uploads/2016/07/IMG-20160728-WA0034-835x467.jpg",
            "https://www.abujaproperties.com/wp-content/uploads/2016/07/IMG-20160728-WA0027-835x467.jpg",
            "https://www.abujaproperties.com/wp-content/uploads/2016/07/IMG-20160728-WA0028-835x467.jpg",
            "https://www.abujaproperties.com/wp-content/uploads/2016/07/IMG-20160728-WA0029-835x467.jpg",
            "https://www.abujaproperties.com/wp-content/uploads/2016/07/IMG-20160728-WA0030-835x467.jpg",
            "https://www.abujaproperties.com/wp-content/uploads/2016/07/IMG-20160728-WA0031-835x467.jpg",
            "https://www.abujaproperties.com/wp-content/uploads/2016/07/IMG-20160728-WA0032-835x467.jpg"
        ],
        "advert_page_link": "https://www.abujaproperties.com/properties/2-bedroom-house-for-sale-at-gaduwa/",
        "page": 21,
        "time_last_updated": 1708057247120
    },
    {
        "property_id": "20582",
        "title": "Lovely 5 Bedroom Duplex at Wuse 2",
        "description": "Well finished 5 bedroom fully detached duplex is available for rent with Boys quarters at Wuse 2, Abuja",
        "listing_type": "Rentals",
        "property_type": "Housing",
        "status": "Available",
        "number_of_page_views": 5683,
        "price": "NGN 15,000,000",
        "property_size": "Not Specified",
        "miscellaneous_details": {
            "rooms": "5",
            "bedrooms": "5",
            "bathrooms": "5",
            "year_built": "2015",
            "garages": "6"
        },
        "address": "Wuse2",
        "city": "Abuja",
        "area": "Wuse II",
        "state": "Not Specified",
        "country": "Nigeria",
        "zip": "Not Specified",
        "location_tags": [
            "Wuse-Ll",
            "Abuja"
        ],
        "contact_info": {
            "contact_address": "Plot 128 Osun Crescent Maitama, Abuja.",
            "phone": "0806 393 3400, 0803 324 9800, 0705 111 6400,",
            "email": "info@abujaproperties.com, abuja@abujaproperties.com"
        },
        "images_urls": [
            "https://www.abujaproperties.com/wp-content/uploads/2017/02/w3-636x467.png",
            "https://www.abujaproperties.com/wp-content/uploads/2017/02/w1-631x467.png",
            "https://www.abujaproperties.com/wp-content/uploads/2017/02/w2-636x467.png",
            "https://www.abujaproperties.com/wp-content/uploads/2017/02/w4-631x467.png",
            "https://www.abujaproperties.com/wp-content/uploads/2017/02/w5-632x467.png",
            "https://www.abujaproperties.com/wp-content/uploads/2017/02/w6-635x467.png",
            "https://www.abujaproperties.com/wp-content/uploads/2017/02/w7-629x467.png",
            "https://www.abujaproperties.com/wp-content/uploads/2017/02/aa1-635x467.png",
            "https://www.abujaproperties.com/wp-content/uploads/2017/02/aa2-641x467.png",
            "https://www.abujaproperties.com/wp-content/uploads/2017/02/aa3-631x467.png",
            "https://www.abujaproperties.com/wp-content/uploads/2017/02/aa4-629x467.png",
            "https://www.abujaproperties.com/wp-content/uploads/2017/02/aa6-632x467.png",
            "https://www.abujaproperties.com/wp-content/uploads/2017/02/aa21-625x467.png",
            "https://www.abujaproperties.com/wp-content/uploads/2017/02/aaa1-610x467.png"
        ],
        "advert_page_link": "https://www.abujaproperties.com/properties/lovely-5-bedroom-duplex-at-wuse-2/",
        "page": 21,
        "time_last_updated": 1708057248666
    },
    {
        "property_id": "20697",
        "title": "Luxury Furnished 4 Bedroom House",
        "description": "Luxury Furnished 4 bedroom detached house with 1 room boys quarter at Maitama is available for rent. This property is in within a good residential district with great facilities and in absolute good condition.",
        "listing_type": "Rentals",
        "property_type": "Housing",
        "status": "Available",
        "number_of_page_views": 1445,
        "price": "NGN 15,000,000",
        "property_size": "Not Specified",
        "miscellaneous_details": {
            "rooms": "4",
            "bedrooms": "4",
            "bathrooms": "4",
            "year_built": "2016",
            "garages": "4"
        },
        "address": "Maitama",
        "city": "Abuja FCT, Maitama",
        "area": "Maitama",
        "state": "Abuja, Abuja FCT",
        "country": "Nigeria",
        "zip": "Not Specified",
        "location_tags": [
            "Maitama",
            "Abuja-Fct",
            "Maitama"
        ],
        "contact_info": {
            "contact_address": "Plot 128 Osun Crescent Maitama, Abuja.",
            "phone": "0806 393 3400, 0803 324 9800, 0705 111 6400,",
            "email": "info@abujaproperties.com, abuja@abujaproperties.com"
        },
        "images_urls": [
            "https://www.abujaproperties.com/wp-content/uploads/2017/02/AQ1-1-522x467.png",
            "https://www.abujaproperties.com/wp-content/uploads/2017/02/AQ2-2-526x467.png",
            "https://www.abujaproperties.com/wp-content/uploads/2017/02/AQ4-2-524x467.png",
            "https://www.abujaproperties.com/wp-content/uploads/2017/02/AQ5-2-527x467.png",
            "https://www.abujaproperties.com/wp-content/uploads/2017/02/AQ6-1-696x467.png",
            "https://www.abujaproperties.com/wp-content/uploads/2017/02/Q3-629x467.png",
            "https://www.abujaproperties.com/wp-content/uploads/2017/02/azx1-638x467.png",
            "https://www.abujaproperties.com/wp-content/uploads/2017/02/azx2-636x467.png",
            "https://www.abujaproperties.com/wp-content/uploads/2017/02/acv22-633x467.png",
            "https://www.abujaproperties.com/wp-content/uploads/2017/02/azce3-636x467.png",
            "https://www.abujaproperties.com/wp-content/uploads/2017/02/asz1-628x467.png",
            "https://www.abujaproperties.com/wp-content/uploads/2017/02/Q1-636x467.png",
            "https://www.abujaproperties.com/wp-content/uploads/2017/02/azc12-638x467.png",
            "https://www.abujaproperties.com/wp-content/uploads/2017/02/Q2-368x467.png"
        ],
        "advert_page_link": "https://www.abujaproperties.com/properties/luxury-furnished-4-bedroom-house-in-maitama/",
        "page": 21,
        "time_last_updated": 1708057250357
    },
    {
        "property_id": "21270",
        "title": "Decent Lovely 5 Bedroom Duplex in Maitama",
        "description": "Decently built and well finished 5 bedroom detached duplex in Maitama for rent with servant quarter\u2019s in a serene environment. \u00a0Features include : All rooms en suite, boys quarter, all rooms en-suites, two sitting rooms, air-conditioners, generator, Intercom, Fully fitted kitchen, Fitted wardrobe, Balcony",
        "listing_type": "Rentals",
        "property_type": "Housing",
        "status": "Available",
        "number_of_page_views": 5695,
        "price": "NGN 15,000,000",
        "property_size": "Not Specified",
        "miscellaneous_details": {
            "rooms": "5",
            "bedrooms": "7",
            "bathrooms": "6",
            "garages": "6"
        },
        "address": "Maitama",
        "city": "Abuja, Maitama",
        "area": "Maitama",
        "state": "Abuja",
        "country": "Nigeria",
        "zip": "Not Specified",
        "location_tags": [
            "Maitama",
            "Abuja",
            "Maitama"
        ],
        "contact_info": {
            "contact_address": "Plot 128 Osun Crescent Maitama, Abuja.",
            "phone": "0806 393 3400, 0803 324 9800, 0705 111 6400,",
            "email": "info@abujaproperties.com, abuja@abujaproperties.com"
        },
        "images_urls": [
            "https://www.abujaproperties.com/wp-content/uploads/2017/10/M1-630x467.png",
            "https://www.abujaproperties.com/wp-content/uploads/2017/10/M2-633x467.png",
            "https://www.abujaproperties.com/wp-content/uploads/2017/10/M3-633x467.png",
            "https://www.abujaproperties.com/wp-content/uploads/2017/10/M4-634x467.png",
            "https://www.abujaproperties.com/wp-content/uploads/2017/10/M5-636x467.png"
        ],
        "advert_page_link": "https://www.abujaproperties.com/properties/lovely-5-bedroom-duplex-in-maitama/",
        "page": 21,
        "time_last_updated": 1708057251896
    },
    {
        "property_id": "20107",
        "title": "Luxury 4 Bedroom Duplex in Maitama",
        "description": "Luxury 4 Bedroom Mansion for rent with bq in Maitama district.",
        "listing_type": "Rentals",
        "property_type": "Housing",
        "status": "Available",
        "number_of_page_views": 5481,
        "price": "NGN 15,000,000",
        "property_size": "2,490.00 sq. ft",
        "miscellaneous_details": {
            "rooms": "4",
            "bedrooms": "4",
            "bathrooms": "4",
            "year_built": "2016",
            "garages": "10"
        },
        "address": "Maitama",
        "city": "Abuja, Maitama",
        "area": "Maitama",
        "state": "Not Specified",
        "country": "Nigeria",
        "zip": "Not Specified",
        "location_tags": [
            "Maitama",
            "Abuja",
            "Maitama"
        ],
        "contact_info": {
            "contact_address": "Plot 128 Osun Crescent Maitama, Abuja.",
            "phone": "0806 393 3400, 0803 324 9800, 0705 111 6400,",
            "email": "info@abujaproperties.com, abuja@abujaproperties.com"
        },
        "images_urls": [
            "https://www.abujaproperties.com/wp-content/uploads/2016/09/IMAG4164-835x467.jpg",
            "https://www.abujaproperties.com/wp-content/uploads/2016/09/IMAG4172-835x467.jpg",
            "https://www.abujaproperties.com/wp-content/uploads/2016/09/IMAG4173-2-835x467.jpg",
            "https://www.abujaproperties.com/wp-content/uploads/2016/09/IMAG4161-835x467.jpg",
            "https://www.abujaproperties.com/wp-content/uploads/2016/09/IMAG4162-835x467.jpg",
            "https://www.abujaproperties.com/wp-content/uploads/2016/09/IMAG4166-835x467.jpg",
            "https://www.abujaproperties.com/wp-content/uploads/2016/09/IMAG4169-835x467.jpg",
            "https://www.abujaproperties.com/wp-content/uploads/2016/09/IMAG4160-835x467.jpg",
            "https://www.abujaproperties.com/wp-content/uploads/2016/09/IMAG4152-835x467.jpg",
            "https://www.abujaproperties.com/wp-content/uploads/2016/09/IMAG4153-835x467.jpg",
            "https://www.abujaproperties.com/wp-content/uploads/2016/09/IMAG4154-835x467.jpg",
            "https://www.abujaproperties.com/wp-content/uploads/2016/09/IMAG4159-835x467.jpg",
            "https://www.abujaproperties.com/wp-content/uploads/2016/09/IMAG4151-835x467.jpg",
            "https://www.abujaproperties.com/wp-content/uploads/2016/09/IMAG4143-835x467.jpg",
            "https://www.abujaproperties.com/wp-content/uploads/2016/09/IMAG4144-835x467.jpg",
            "https://www.abujaproperties.com/wp-content/uploads/2016/09/IMAG4148-835x467.jpg",
            "https://www.abujaproperties.com/wp-content/uploads/2016/09/IMAG4141-1-835x467.jpg",
            "https://www.abujaproperties.com/wp-content/uploads/2016/09/IMAG4139-835x467.jpg"
        ],
        "advert_page_link": "https://www.abujaproperties.com/properties/luxury-4-bedroom-duplex-in-maitama/",
        "page": 21,
        "time_last_updated": 1708057253445
    },
    {
        "property_id": "25352",
        "title": "Luxury 12 units of 3 & 2 Bedroom Apartments",
        "description": "Brand new Luxury 3 & 2 Bedroom apartment located at Wuse 2 district is available for rent.",
        "listing_type": "Rentals",
        "property_type": "Housing",
        "status": "Available",
        "number_of_page_views": 427,
        "price": "NGN 15,000,000",
        "property_size": "7,433.00 sq. ft",
        "miscellaneous_details": {
            "rooms": "3",
            "bedrooms": "4",
            "bathrooms": "4"
        },
        "address": "Not Specified",
        "city": "Abuja, Abuja FCT",
        "area": "Not Specified",
        "state": "Abuja, Abuja FCT, Federal Capital Territory",
        "country": "Nigeria",
        "zip": "Not Specified",
        "location_tags": [
            "Abuja",
            "Abuja-Fct"
        ],
        "contact_info": {
            "contact_address": "Plot 128 Osun Crescent Maitama, Abuja.",
            "phone": "0806 393 3400, 0803 324 9800, 0705 111 6400,",
            "email": "info@abujaproperties.com, abuja@abujaproperties.com"
        },
        "images_urls": [
            "https://www.abujaproperties.com/wp-content/uploads/2023/03/AE1-687x467.png",
            "https://www.abujaproperties.com/wp-content/uploads/2023/03/AE2-687x467.png",
            "https://www.abujaproperties.com/wp-content/uploads/2023/03/AE3-686x467.png",
            "https://www.abujaproperties.com/wp-content/uploads/2023/03/AE4-700x467.png",
            "https://www.abujaproperties.com/wp-content/uploads/2023/03/AE5-694x467.png",
            "https://www.abujaproperties.com/wp-content/uploads/2023/03/AE6-695x467.png",
            "https://www.abujaproperties.com/wp-content/uploads/2023/03/AE7-696x467.png",
            "https://www.abujaproperties.com/wp-content/uploads/2023/03/AE8-384x467.png"
        ],
        "advert_page_link": "https://www.abujaproperties.com/properties/luxury-12-units-of-3-2-bedroom-apartments/",
        "page": 21,
        "time_last_updated": 1708057255028
    },
    {
        "property_id": "18978",
        "title": "4 Bedroom House for Rent at Maitama",
        "description": "A decently built and well designed four bedroom house is available for sale at Maitama. This property is located at a very serene environment and has ample parking space. Good for residential purpose, Facilities includes: Elevators, air-conditioners, Intercom, Jacuzzi, Fitted kitchen, Pent house, \u00a0parking space for five cars, study room, boys quarter.",
        "listing_type": "Rentals",
        "property_type": "Housing",
        "status": "Available",
        "number_of_page_views": 1489,
        "price": "NGN 15,000,000",
        "property_size": "Not Specified",
        "miscellaneous_details": {
            "rooms": "4",
            "bedrooms": "5",
            "bathrooms": "5",
            "year_built": "2016",
            "garages": "5"
        },
        "address": "Maitama",
        "city": "Maitama",
        "area": "Maitama",
        "state": "Not Specified",
        "country": "Nigeria",
        "zip": "Not Specified",
        "location_tags": [
            "Maitama",
            "Maitama"
        ],
        "contact_info": {
            "contact_address": "Plot 128 Osun Crescent Maitama, Abuja.",
            "phone": "0806 393 3400, 0803 324 9800, 0705 111 6400,",
            "email": "info@abujaproperties.com, abuja@abujaproperties.com"
        },
        "images_urls": [
            "https://www.abujaproperties.com/wp-content/uploads/2016/02/IMAG1993_1-835x467.jpg",
            "https://www.abujaproperties.com/wp-content/uploads/2016/02/IMAG1998-835x467.jpg",
            "https://www.abujaproperties.com/wp-content/uploads/2016/02/IMAG1999-835x467.jpg",
            "https://www.abujaproperties.com/wp-content/uploads/2016/02/IMAG2000-835x467.jpg",
            "https://www.abujaproperties.com/wp-content/uploads/2016/02/IMAG2004-835x467.jpg",
            "https://www.abujaproperties.com/wp-content/uploads/2016/02/IMAG2006-835x467.jpg",
            "https://www.abujaproperties.com/wp-content/uploads/2016/02/IMAG2008-835x467.jpg",
            "https://www.abujaproperties.com/wp-content/uploads/2016/02/IMAG2014-835x467.jpg",
            "https://www.abujaproperties.com/wp-content/uploads/2016/02/IMAG2017_1-835x467.jpg",
            "https://www.abujaproperties.com/wp-content/uploads/2016/01/IMAG2558-835x467.jpg",
            "https://www.abujaproperties.com/wp-content/uploads/2016/01/IMAG2559-835x467.jpg",
            "https://www.abujaproperties.com/wp-content/uploads/2016/01/IMAG2560-835x467.jpg",
            "https://www.abujaproperties.com/wp-content/uploads/2016/01/IMAG2561-835x467.jpg",
            "https://www.abujaproperties.com/wp-content/uploads/2016/01/IMAG2565-835x467.jpg",
            "https://www.abujaproperties.com/wp-content/uploads/2016/01/IMAG2566-835x467.jpg",
            "https://www.abujaproperties.com/wp-content/uploads/2016/01/IMAG2567-835x467.jpg",
            "https://www.abujaproperties.com/wp-content/uploads/2016/01/IMAG2571-835x467.jpg",
            "https://www.abujaproperties.com/wp-content/uploads/2016/01/IMAG2568-1-835x467.jpg"
        ],
        "advert_page_link": "https://www.abujaproperties.com/properties/new-4-bedroom-house-for-rent-at-maitama/",
        "page": 21,
        "time_last_updated": 1708057256682
    },
    {
        "property_id": "17686",
        "title": "6 Bedroom Duplex for Rent in Maitama",
        "description": "Fully serviced and furnished 6 bedroom detached duplex with 2 boys quarters, ample parking space is available for rent in Maitama district.",
        "listing_type": "Rentals",
        "property_type": "Housing",
        "status": "Available",
        "number_of_page_views": 5856,
        "price": "NGN 15,000,000",
        "property_size": "1,000.00 sq. ft",
        "miscellaneous_details": {
            "property_lot_size": "600.00 ft2",
            "rooms": "6",
            "bedrooms": "6",
            "bathrooms": "6",
            "year_built": "2010"
        },
        "address": "Maitama",
        "city": "Abuja, Maitama",
        "area": "Maitama",
        "state": "Not Specified",
        "country": "Nigeria",
        "zip": "Not Specified",
        "location_tags": [
            "Maitama",
            "Abuja",
            "Maitama"
        ],
        "contact_info": "None",
        "images_urls": [
            "https://www.abujaproperties.com/wp-content/uploads/2014/05/IMAG1261-835x467.jpg",
            "https://www.abujaproperties.com/wp-content/uploads/2014/05/IMAG1246-835x467.jpg",
            "https://www.abujaproperties.com/wp-content/uploads/2014/05/IMAG1252-835x467.jpg",
            "https://www.abujaproperties.com/wp-content/uploads/2014/05/IMAG1253-835x467.jpg",
            "https://www.abujaproperties.com/wp-content/uploads/2014/05/IMAG1255-835x467.jpg",
            "https://www.abujaproperties.com/wp-content/uploads/2014/05/IMAG1258-835x467.jpg",
            "https://www.abujaproperties.com/wp-content/uploads/2014/05/IMAG1259-835x467.jpg"
        ],
        "advert_page_link": "https://www.abujaproperties.com/properties/massive6bed/",
        "page": 21,
        "time_last_updated": 1708057258220
    },
    {
        "property_id": "18598",
        "title": "8 Bedroom Detached Duplex at Maitama",
        "description": "A massive 8 bedroom detached duplex is available for rent at Maitama, this property can serve for both commercial and residential purpose and has large space and big rooms.",
        "listing_type": "Rentals",
        "property_type": "Housing",
        "status": "Available",
        "number_of_page_views": 1212,
        "price": "NGN 15,000,000",
        "property_size": "Not Specified",
        "miscellaneous_details": {
            "rooms": "8",
            "bedrooms": "8",
            "bathrooms": "8",
            "year_built": "2011"
        },
        "address": "Maitama",
        "city": "Maitama",
        "area": "Maitama",
        "state": "Not Specified",
        "country": "Nigeria",
        "zip": "Not Specified",
        "location_tags": [
            "Maitama",
            "Maitama"
        ],
        "contact_info": {
            "contact_address": "Plot 128 Osun Crescent Maitama, Abuja.",
            "phone": "0806 393 3400, 0803 324 9800, 0705 111 6400,",
            "email": "info@abujaproperties.com, abuja@abujaproperties.com"
        },
        "images_urls": [
            "https://www.abujaproperties.com/wp-content/uploads/2016/01/IMAG1635-835x467.jpg",
            "https://www.abujaproperties.com/wp-content/uploads/2016/01/IMAG1638-835x467.jpg",
            "https://www.abujaproperties.com/wp-content/uploads/2016/01/IMAG1641-835x467.jpg",
            "https://www.abujaproperties.com/wp-content/uploads/2016/01/IMAG1645-835x467.jpg",
            "https://www.abujaproperties.com/wp-content/uploads/2016/01/IMAG1646-835x467.jpg",
            "https://www.abujaproperties.com/wp-content/uploads/2016/01/IMAG1648-835x467.jpg",
            "https://www.abujaproperties.com/wp-content/uploads/2016/01/IMAG1649-835x467.jpg"
        ],
        "advert_page_link": "https://www.abujaproperties.com/properties/8-bedroom-detached-duplex-at-maitama/",
        "page": 21,
        "time_last_updated": 1708057260252
    },
    {
        "property_id": "19201",
        "title": "2 Bedroom Bungalow with Green Area at Maitama",
        "description": "An absolutely lovely and fully furnished two bedroom luxury bungalow is available for rent. The pictures here says it all. This house was built with the best of Italian design.",
        "listing_type": "Rentals",
        "property_type": "Housing",
        "status": "Available",
        "number_of_page_views": 1554,
        "price": "NGN 15,000,000",
        "property_size": "Not Specified",
        "miscellaneous_details": {
            "rooms": "2",
            "bedrooms": "3",
            "bathrooms": "3",
            "year_built": "2015"
        },
        "address": "Maitama",
        "city": "Maitama",
        "area": "Maitama",
        "state": "Abuja, Abuja FCT, Federal Capital Territory",
        "country": "Nigeria",
        "zip": "Not Specified",
        "location_tags": [
            "Maitama",
            "Maitama"
        ],
        "contact_info": {
            "contact_address": "Plot 128 Osun Crescent Maitama, Abuja.",
            "phone": "0806 393 3400, 0803 324 9800, 0705 111 6400,",
            "email": "info@abujaproperties.com, abuja@abujaproperties.com"
        },
        "images_urls": [
            "https://www.abujaproperties.com/wp-content/uploads/2016/03/IMAG2362-835x467.jpg",
            "https://www.abujaproperties.com/wp-content/uploads/2016/03/IMAG2352-835x467.jpg",
            "https://www.abujaproperties.com/wp-content/uploads/2016/03/IMAG2353-835x467.jpg",
            "https://www.abujaproperties.com/wp-content/uploads/2016/03/IMAG2354-835x467.jpg",
            "https://www.abujaproperties.com/wp-content/uploads/2016/03/IMAG2356-835x467.jpg",
            "https://www.abujaproperties.com/wp-content/uploads/2016/03/IMAG2363-835x467.jpg"
        ],
        "advert_page_link": "https://www.abujaproperties.com/properties/2-bedroom-bungalow-with-green-area-at-maitama/",
        "page": 21,
        "time_last_updated": 1708057262265
    },
    {
        "property_id": "23468",
        "title": "Luxury 5 bedroom Duplex in Asokoro",
        "description": "Tastefully finished 5 bedroom detached duplex is available for rent in Asokoro Abuja.",
        "listing_type": "Rentals",
        "property_type": "Housing",
        "status": "Available",
        "number_of_page_views": 1192,
        "price": "NGN 15,000,000",
        "property_size": "1,200.00 sq. ft",
        "miscellaneous_details": {
            "rooms": "8",
            "bedrooms": "8",
            "bathrooms": "8"
        },
        "address": "Not Specified",
        "city": "Abuja, Abuja FCT",
        "area": "Asokoro",
        "state": "Abuja, Abuja FCT",
        "country": "Nigeria",
        "zip": "Not Specified",
        "location_tags": [
            "Asokoro",
            "Abuja",
            "Abuja-Fct"
        ],
        "contact_info": {
            "contact_address": "Plot 128 Osun Crescent Maitama, Abuja.",
            "phone": "0806 393 3400, 0803 324 9800, 0705 111 6400,",
            "email": "info@abujaproperties.com, abuja@abujaproperties.com"
        },
        "images_urls": [
            "https://www.abujaproperties.com/wp-content/uploads/2020/11/AX22A-651x467.png",
            "https://www.abujaproperties.com/wp-content/uploads/2020/11/AX1A-667x467.png",
            "https://www.abujaproperties.com/wp-content/uploads/2020/11/AX2-1-650x467.png",
            "https://www.abujaproperties.com/wp-content/uploads/2020/11/AX2A-661x467.png",
            "https://www.abujaproperties.com/wp-content/uploads/2020/11/AX3-661x467.png",
            "https://www.abujaproperties.com/wp-content/uploads/2020/11/AX3A-659x467.png",
            "https://www.abujaproperties.com/wp-content/uploads/2020/11/AX4-661x467.png",
            "https://www.abujaproperties.com/wp-content/uploads/2020/11/AX5-655x467.png",
            "https://www.abujaproperties.com/wp-content/uploads/2020/11/AX6-648x467.png"
        ],
        "advert_page_link": "https://www.abujaproperties.com/properties/luxury-5-bedroom-duplex-in-asokoro/",
        "page": 21,
        "time_last_updated": 1708057263936
    }
]